gagan/__init__.py
gagan/errors.py
gagan/interpreter.py
gagan/lexer.py
gagan/parser.py
gagan_lang-0.4.dist-info/LICENSE
gagan_lang-0.4.dist-info/METADATA
gagan_lang-0.4.dist-info/WHEEL
gagan_lang-0.4.dist-info/entry_points.txt
gagan_lang-0.4.dist-info/top_level.txt
gagan_lang-0.4.dist-info/RECORD
