Metadata-Version: 2.2
Name: gagan-lang
Version: 0.4
Summary: The world's simplest programming language.
Home-page: https://github.com/higgn/gagan-lang
Author: Gagan
Author-email: imgaganhonor@gmail.com
Classifier: Programming Language :: Python :: 3
Classifier: License :: OSI Approved :: MIT License
Classifier: Operating System :: OS Independent
Requires-Python: >=3.7
License-File: LICENSE
Dynamic: author
Dynamic: author-email
Dynamic: classifier
Dynamic: description
Dynamic: description-content-type
Dynamic: home-page
Dynamic: requires-python
Dynamic: summary
